profitgraph/__init__.py
profitgraph/add_data.py
profitgraph/create_data.py
profitgraph/db.py
profitgraph/graph.py
profitgraph/language.py
profitgraph/main.py
profitgraph/random_data.py
profitgraph-0.8.3.dist-info/LICENSE.md
profitgraph-0.8.3.dist-info/METADATA
profitgraph-0.8.3.dist-info/WHEEL
profitgraph-0.8.3.dist-info/entry_points.txt
profitgraph-0.8.3.dist-info/top_level.txt
profitgraph-0.8.3.dist-info/RECORD
