Metadata-Version: 2.1
Name: profitgraph
Version: 0.8.3
Summary: Small program that creates graphs based on date, profit or purchases
Home-page: https://github.com/Morjovski/profit_graph
Author: Morjovski
Author-email: amor3ux@gmail.com
License: MIT License
Keywords: profits,graphs,analytics
Platform: ALL
Classifier: Development Status :: 4 - Beta
Classifier: Topic :: Utilities
Classifier: License :: OSI Approved :: MIT License
Classifier: Programming Language :: Python :: 3
License-File: LICENSE.md
Requires-Dist: matplotlib (~=3.6.2)
Requires-Dist: mplcursors (~=0.5.2)
Requires-Dist: tqdm (~=4.64.1)
Requires-Dist: colorama (~=0.4.6)
